minipyer/__init__.py
minipyer/lib/__init__.py
minipyer/lib/css_minipyer.py
minipyer/lib/minipyer.py
minipyer-0.1.0.dist-info/LICENSE
minipyer-0.1.0.dist-info/METADATA
minipyer-0.1.0.dist-info/WHEEL
minipyer-0.1.0.dist-info/top_level.txt
minipyer-0.1.0.dist-info/RECORD
