Metadata-Version: 2.1
Name: minipyer
Version: 0.1.0
Summary: minipyer is a code minifier python package. You can use this package to minipy your codes. =)
Home-page: https://github.com/MPCodeWriter21/minipyer
Author: CodeWriter21(Mehrad Pooryoussof)
Author-email: <CodeWriter21@gmail.com>
License: Apache-2.0 License
Keywords: python,minify,minipy,minipyer,code
Platform: UNKNOWN
Classifier: Intended Audience :: Developers
Classifier: Programming Language :: Python :: 3.10
Classifier: Operating System :: Unix
Classifier: Operating System :: MacOS :: MacOS X
Classifier: Operating System :: Microsoft :: Windows
License-File: LICENSE
